azure/mgmt/security/__init__.py
azure/mgmt/security/_configuration.py
azure/mgmt/security/_security_center.py
azure/mgmt/security/_serialization.py
azure/mgmt/security/_version.py
azure/mgmt/security/models.py
azure/mgmt/security/py.typed
azure/mgmt/security/aio/__init__.py
azure/mgmt/security/aio/_configuration.py
azure/mgmt/security/aio/_security_center.py
azure/mgmt/security/v2015_06_01_preview/__init__.py
azure/mgmt/security/v2015_06_01_preview/_configuration.py
azure/mgmt/security/v2015_06_01_preview/_patch.py
azure/mgmt/security/v2015_06_01_preview/_security_center.py
azure/mgmt/security/v2015_06_01_preview/_vendor.py
azure/mgmt/security/v2015_06_01_preview/_version.py
azure/mgmt/security/v2015_06_01_preview/aio/__init__.py
azure/mgmt/security/v2015_06_01_preview/aio/_configuration.py
azure/mgmt/security/v2015_06_01_preview/aio/_patch.py
azure/mgmt/security/v2015_06_01_preview/aio/_security_center.py
azure/mgmt/security/v2015_06_01_preview/aio/operations/__init__.py
azure/mgmt/security/v2015_06_01_preview/aio/operations/_locations_operations.py
azure/mgmt/security/v2015_06_01_preview/aio/operations/_operations.py
azure/mgmt/security/v2015_06_01_preview/aio/operations/_patch.py
azure/mgmt/security/v2015_06_01_preview/aio/operations/_tasks_operations.py
azure/mgmt/security/v2015_06_01_preview/models/__init__.py
azure/mgmt/security/v2015_06_01_preview/models/_models_py3.py
azure/mgmt/security/v2015_06_01_preview/models/_patch.py
azure/mgmt/security/v2015_06_01_preview/models/_security_center_enums.py
azure/mgmt/security/v2015_06_01_preview/operations/__init__.py
azure/mgmt/security/v2015_06_01_preview/operations/_locations_operations.py
azure/mgmt/security/v2015_06_01_preview/operations/_operations.py
azure/mgmt/security/v2015_06_01_preview/operations/_patch.py
azure/mgmt/security/v2015_06_01_preview/operations/_tasks_operations.py
azure/mgmt/security/v2017_08_01/__init__.py
azure/mgmt/security/v2017_08_01/_configuration.py
azure_mgmt_security-7.0.0.dist-info/LICENSE
azure_mgmt_security-7.0.0.dist-info/METADATA
azure_mgmt_security-7.0.0.dist-info/WHEEL
azure_mgmt_security-7.0.0.dist-info/top_level.txt
azure_mgmt_security-7.0.0.dist-info/RECORD
